langgraph_checkpoint_s3/__init__.py
langgraph_checkpoint_s3/aio.py
langgraph_checkpoint_s3/checkpoint.py
langgraph_checkpoint_s3/utils.py
langgraph_checkpoint_s3/cli/__init__.py
langgraph_checkpoint_s3/cli/main.py
langgraph_checkpoint_s3/cli/reader.py
langgraph_checkpoint_s3-0.1.3.dist-info/METADATA
langgraph_checkpoint_s3-0.1.3.dist-info/WHEEL
langgraph_checkpoint_s3-0.1.3.dist-info/entry_points.txt
langgraph_checkpoint_s3-0.1.3.dist-info/licenses/LICENSE
langgraph_checkpoint_s3-0.1.3.dist-info/RECORD
