Metadata-Version: 2.4
Name: langgraph-checkpoint-s3
Version: 0.1.3
Summary: A Python library for LangGraph checkpoint storage using S3
Project-URL: Homepage, https://github.com/Isa-rentacs/langgraph-checkpoint-s3
Project-URL: Repository, https://github.com/Isa-rentacs/langgraph-checkpoint-s3
Project-URL: Documentation, https://langgraph-checkpoint-s3.readthedocs.io
Project-URL: Issues, https://github.com/Isa-rentacs/langgraph-checkpoint-s3/issues
Author-email: Jun Kuroda <jkuroda.isa@gmail.com>
License: MIT
License-File: LICENSE
Keywords: checkpoint,langgraph,s3,storage
Classifier: Development Status :: 3 - Alpha
Classifier: Intended Audience :: Developers
Classifier: License :: OSI Approved :: MIT License
Classifier: Programming Language :: Python :: 3
Classifier: Programming Language :: Python :: 3.10
Classifier: Programming Language :: Python :: 3.11
Classifier: Programming Language :: Python :: 3.12
Classifier: Programming Language :: Python :: 3.13
Classifier: Programming Language :: Python :: 3.14
Requires-Python: >=3.10
Requires-Dist: aioboto3>=15.2.0
Requires-Dist: boto3>=1.26.0
Requires-Dist: botocore>=1.29.0
Requires-Dist: click>=8.0.0
Requires-Dist: langgraph-checkpoint>=2.1.0
Provides-Extra: dev
Requires-Dist: mypy>=1.0.0; extra == 'dev'
Requires-Dist: pre-commit>=2.20.0; extra == 'dev'
Requires-Dist: pytest-cov>=4.0.0; extra == 'dev'
Requires-Dist: pytest>=7.0.0; extra == 'dev'
Requires-Dist: ruff>=0.1.0; extra == 'dev'
Requires-Dist: types-aioboto3[s3]>=12.0.0; extra == 'dev'
Requires-Dist: types-boto3-s3>=1.40.0; extra == 'dev'
Provides-Extra: docs
Requires-Dist: sphinx-rtd-theme>=1.0.0; extra == 'docs'
Requires-Dist: sphinx>=5.0.0; extra == 'docs'
